buzz/__init__.py
buzz/buzz.py
buzz/test_buzz.py
buzzlang-0.1.0.dist-info/METADATA
buzzlang-0.1.0.dist-info/WHEEL
buzzlang-0.1.0.dist-info/top_level.txt
buzzlang-0.1.0.dist-info/RECORD
